AUTHORS
CHANGELOG.txt
DESCRIPTION
LICENSE
MANIFEST.in
README.rst
setup.cfg
setup.py
django_mailer_throttled.egg-info/PKG-INFO
django_mailer_throttled.egg-info/SOURCES.txt
django_mailer_throttled.egg-info/dependency_links.txt
django_mailer_throttled.egg-info/requires.txt
django_mailer_throttled.egg-info/top_level.txt
mailer_throttled/__init__.py
mailer_throttled/models.py
mailer_throttled/management/__init__.py
mailer_throttled/management/commands/__init__.py
mailer_throttled/management/commands/send_mail_throttled.py