Metadata-Version: 1.0
Name: django-mailer-throttled
Version: 0.1
Summary: Addon for django-mailer that allows to send throttled emails
